openlineage/dagster/__init__.py
openlineage/dagster/adapter.py
openlineage/dagster/cursor.py
openlineage/dagster/sensor.py
openlineage/dagster/utils.py
openlineage_dagster-1.38.0.dist-info/METADATA
openlineage_dagster-1.38.0.dist-info/WHEEL
openlineage_dagster-1.38.0.dist-info/top_level.txt
openlineage_dagster-1.38.0.dist-info/RECORD
