Metadata-Version: 2.4
Name: openlineage-dagster
Version: 1.38.0
Summary: OpenLineage integration with Dagster
Author: OpenLineage
Keywords: openlineage
Requires-Python: >=3.9
Requires-Dist: attrs>=19.3
Requires-Dist: cattrs
Requires-Dist: protobuf<6,>4
Requires-Dist: dagster<=1.6.9,>=1.0.0
Requires-Dist: openlineage-python==1.38.0
Provides-Extra: tests
Requires-Dist: pytest; extra == "tests"
Requires-Dist: pytest-cov; extra == "tests"
Requires-Dist: mypy>=0.9.6; extra == "tests"
Requires-Dist: pydantic<2.0.0; extra == "tests"
Requires-Dist: sqlalchemy<2.0.0; extra == "tests"
Provides-Extra: dev
Requires-Dist: pytest; extra == "dev"
Requires-Dist: pytest-cov; extra == "dev"
Requires-Dist: mypy>=0.9.6; extra == "dev"
Requires-Dist: pydantic<2.0.0; extra == "dev"
Requires-Dist: sqlalchemy<2.0.0; extra == "dev"
Dynamic: author
Dynamic: description
Dynamic: description-content-type
Dynamic: keywords
Dynamic: provides-extra
Dynamic: requires-dist
Dynamic: requires-python
Dynamic: summary
